{
    "title": "Device Control Center",
    "url": "https://github.com/NeonGeckoCom/skill-device_controls",
    "summary": "Handles system-wide settings and controls.",
    "short_description": "Handles system-wide settings and controls.",
    "description": "Device Control skill handles global core configuration and OS interactions (via messagebus/PHAL service).",
    "examples": [
        "Skip wake words.",
        "Require wake words.",
        "I want you to exit.",
        "I want you to shut down.",
        "I want you to restart."
    ],
    "desktopFile": false,
    "warning": "",
    "systemDeps": false,
    "requirements": {
        "python": [
            "neon-utils~=1.0",
            "ovos-bus-client~=0.0.3",
            "ovos-utils~=0.0.28"
        ],
        "system": {},
        "skill": []
    },
    "incompatible_skills": [],
    "platforms": [
        "i386",
        "x86_64",
        "ia64",
        "arm64",
        "arm"
    ],
    "branch": "master",
    "license": "BSD-3-Clause",
    "icon": "https://0000.us/klatchat/app/files/neon_images/icons/neon_skill.png",
    "category": "Configuration",
    "categories": [
        "Configuration",
        "Daily"
    ],
    "tags": [
        "NeonGecko Original",
        "NeonAI",
        "controls",
        "device",
        "wake words",
        "power",
        "settings"
    ],
    "credits": [
        "NeonGeckoCom",
        "NeonDaniel",
        "reginaneon"
    ],
    "skillname": "skill-device_controls",
    "authorname": "NeonGeckoCom",
    "foldername": null
}